src/generic_counter.sv
`timescale 1ns / 1ps

//TODO Marlin does not support constant expression for now
module generic_counter #(
    parameter unsigned MAX =1280,
    parameter unsigned ONESHOT = 0,
    parameter unsigned N = $clog2(MAX)
) (
    input clk,
    input rstn,
    input en,

    output [N - 1:0] x,

    output ending
);
  reg [N - 1:0] counter = 0;

  assign ending = counter == N'(MAX - 1);

  always @(posedge clk, negedge rstn) begin
    if (!rstn) begin
      counter <= 0;
    end else begin
      if (en) counter <= ending ? (ONESHOT ? counter : 0) : counter + 1;
    end
  end

  assign x = counter;
endmodule

module test_generic_counter (
    input clk,
    input rstn,
    input en,

    output [3:0] x,

    output ending
);
  generic_counter #(
      .MAX(16),
      .N  (4)
  ) cnt (
      .clk(clk),
      .rstn(rstn),
      .en(en),
      .x(x),
      .ending(ending)
  );

endmodule

tests/test_counter.vcd
$version Generated by VerilatedVcd $end
$timescale 1ps $end
 $scope module TOP $end
  $var wire 1 " clk $end
  $var wire 1 # rstn $end
  $var wire 1 $ en $end
  $var wire 4 % x [3:0] $end
  $var wire 1 & ending $end
  $scope module test_generic_counter $end
   $var wire 1 " clk $end
   $var wire 1 # rstn $end
   $var wire 1 $ en $end
   $var wire 4 % x [3:0] $end
   $var wire 1 & ending $end
   $scope module cnt $end
    $var wire 32 ' MAX [31:0] $end
    $var wire 32 ( ONESHOT [31:0] $end
    $var wire 32 ) N [31:0] $end
    $var wire 1 " clk $end
    $var wire 1 # rstn $end
    $var wire 1 $ en $end
    $var wire 4 % x [3:0] $end
    $var wire 1 & ending $end
    $var wire 4 % counter [3:0] $end
   $upscope $end
  $upscope $end
 $upscope $end
 $scope module TOP $end
  $var wire 1 * clk $end
  $var wire 1 + rstn $end
  $var wire 1 , en $end
  $var wire 4 - x [3:0] $end
  $var wire 1 . ending $end
  $scope module test_generic_counter $end
   $var wire 1 * clk $end
   $var wire 1 + rstn $end
   $var wire 1 , en $end
   $var wire 4 - x [3:0] $end
   $var wire 1 . ending $end
   $scope module cnt $end
    $var wire 32 / MAX [31:0] $end
    $var wire 32 0 ONESHOT [31:0] $end
    $var wire 32 1 N [31:0] $end
    $var wire 1 * clk $end
    $var wire 1 + rstn $end
    $var wire 1 , en $end
    $var wire 4 - x [3:0] $end
    $var wire 1 . ending $end
    $var wire 4 - counter [3:0] $end
   $upscope $end
  $upscope $end
 $upscope $end
$enddefinitions $end


#0
1"
0#
0$
b0000 %
0&
0*
0+
0,
b0000 -
0.
b00000000000000000000000000010000 '
b00000000000000000000000000000000 (
b00000000000000000000000000000100 )
b00000000000000000000000000010000 /
b00000000000000000000000000000000 0
b00000000000000000000000000000100 1
#1
1*
#2
0*
1+
1,
#3
1*
b0001 -
#4
0*
#5
1*
b0010 -
#6
0*
#7
1*
b0011 -
#8
0*
#9
1*
b0100 -
#10
0*
#11
1*
b0101 -
#12
0*
#13
1*
b0110 -
#14
0*
#15
1*
b0111 -
#16
0*
#17
1*
b1000 -
#18
0*
#19
1*
b1001 -
#20
0*
#21
1*
b1010 -
#22
0*
#23
1*
b1011 -
#24
0*
#25
1*
b1100 -
#26
0*
#27
1*
b1101 -
#28
0*
#29
1*
b1110 -
#30
0*
#31
1*
b1111 -
1.
